LICENSE
MANIFEST.in
README.md
setup.py
omdbapi/__init__.py
omdbapi/movie_search.py
omdbapi.egg-info/PKG-INFO
omdbapi.egg-info/SOURCES.txt
omdbapi.egg-info/dependency_links.txt
omdbapi.egg-info/not-zip-safe
omdbapi.egg-info/requires.txt
omdbapi.egg-info/top_level.txt
omdbapi/tests/__init__.py
omdbapi/tests/test_movie.py