Metadata-Version: 2.1
Name: omdbapi
Version: 0.7.0
Summary: Wrapper to get movie, series, episode data from the Open Movie Database (OMDb) api.
Home-page: https://github.com/dubirajara/omdbapi
Author: Diego Ubirajara
Author-email: diego.ubirajara@mail.com
License: GNU AFFERO GENERAL PUBLIC LICENSE
Classifier: Development Status :: 2 - Pre-Alpha
Classifier: Environment :: Console
Classifier: Intended Audience :: Developers
Classifier: License :: OSI Approved :: GNU Affero General Public License v3 or later (AGPLv3+)
Classifier: Operating System :: OS Independent
Classifier: Programming Language :: Python
Classifier: Programming Language :: Python :: 3.7
Classifier: Framework :: Pytest
License-File: LICENSE
